diffpy.magpdf-0.0.0-py2.7-nspkg.pth
diffpy/magpdf/__init__.py
diffpy/magpdf/gitarchive.cfg
diffpy/magpdf/magstructure.py
diffpy/magpdf/mpdfcalculator.py
diffpy/magpdf/version.cfg
diffpy/magpdf/version.py
diffpy/magpdf/tests/MnO_cubic.cif
diffpy/magpdf/tests/__init__.py
diffpy/magpdf/tests/run.py
diffpy/magpdf/tests/testbasicmpdf.py
diffpy/magpdf/tests/testdata.fgr
diffpy/magpdf/tests/testformfactor.py
diffpy/magpdf/tests/testgetdiffdata.py
diffpy/magpdf/tests/testmpdffromcif.py
diffpy/magpdf/tests/testmpdffromselfcreated.py
diffpy/magpdf/tests/testspinsatoms.py
diffpy/magpdf/tests/testdata/MnO_cubic.cif
diffpy/magpdf/tests/testdata/testdata.fgr
diffpy.magpdf-0.0.0.dist-info/DESCRIPTION.rst
diffpy.magpdf-0.0.0.dist-info/METADATA
diffpy.magpdf-0.0.0.dist-info/RECORD
diffpy.magpdf-0.0.0.dist-info/WHEEL
diffpy.magpdf-0.0.0.dist-info/metadata.json
diffpy.magpdf-0.0.0.dist-info/namespace_packages.txt
diffpy.magpdf-0.0.0.dist-info/top_level.txt
