Metadata-Version: 2.0
Name: diffpy.magpdf
Version: 0.0.0
Summary: Tools for magnetic PDF analysis.
Home-page: https://github.com/benfrandsen/diffpy.magpdf/
Author: Benjamin Frandsen
Author-email: benfrandsen@gmail.com
License: BSD-style license
Keywords: mPDF magnetic PDF
Platform: UNKNOWN
Classifier: Development Status :: 5 - Production/Stable
Classifier: Environment :: Console
Classifier: Intended Audience :: Developers
Classifier: Intended Audience :: Science/Research
Classifier: License :: OSI Approved :: BSD License
Classifier: Operating System :: MacOS :: MacOS X
Classifier: Operating System :: Microsoft :: Windows
Classifier: Operating System :: POSIX
Classifier: Operating System :: Unix
Classifier: Programming Language :: Python :: 2.6
Classifier: Programming Language :: Python :: 2.7
Classifier: Topic :: Scientific/Engineering :: Physics
